phonix/__init__.py
phonix/components/__init__.py
phonix/components/api.py
phonix/components/monitoring/__init__.py
phonix/components/monitoring/component.py
phonix/components/monitoring/monitoring/__init__.py
phonix/components/monitoring/monitoring/binding.py
phonix/components/monitoring/monitoring/commands_handler.py
phonix/components/monitoring/monitoring/debugging.py
phonix/components/monitoring/monitoring/plotting.py
phonix/components/monitoring/monitoring/silence_level_handler.py
phonix/components/monitoring/monitoring/sound_level_handler.py
phonix/components/monitoring/monitoring/states_handler.py
phonix/components/recording/__init__.py
phonix/components/recording/component.py
phonix/components/recording/recording_request.py
phonix/daemon/__init__.py
phonix/daemon/daemon/__init__.py
phonix/daemon/daemon/console_monitor.py
phonix/daemon/daemon/daemon.py
phonix/daemon/daemon/events.py
phonix/daemon/daemon/utils.py
phonix/daemon/daemon/volume.py
phonix/daemon/daemon/volume_deamon.py
phonix/daemon/daemon/files/beep_error.wav
phonix/daemon/daemon/files/beep_hi.wav
phonix/daemon/daemon/files/beep_lo.wav
phonix/daemon/inputs/__init__.py
phonix/daemon/inputs/audio_input.py
phonix/daemon/inputs/fake_input.py
phonix/daemon/inputs/pyaudio_input.py
phonix/daemon/outputs/__init__.py
phonix/daemon/outputs/audio_output.py
phonix/daemon/outputs/fake_audio_output.py
phonix/daemon/outputs/play_output.py
phonix/daemon/outputs/pyaudio_output.py
phonix/daemon/processing/__init__.py
phonix/daemon/processing/core.py
phonix/daemon/processing/level_reporting_unit.py
phonix/daemon/processing/mic_recording.py
phonix/daemon/processing/porcupine_wake_word_unit_new_version.py
phonix/daemon/processing/porcupine_wake_word_unit_old_version.py
phonix/daemon/processing/recording_unit.py
phonix/daemon/processing/silence_margin_unit.py
phonix/daemon/processing/sound_buffer.py
phonix/daemon/processing/too_long_open_mic_unit.py
kaia_phonix-4.0.9.dist-info/METADATA
kaia_phonix-4.0.9.dist-info/WHEEL
kaia_phonix-4.0.9.dist-info/top_level.txt
kaia_phonix-4.0.9.dist-info/RECORD
